MANIFEST.in
README.md
VERSION
setup.py
aegisx.ext.jose.egg-info/PKG-INFO
aegisx.ext.jose.egg-info/SOURCES.txt
aegisx.ext.jose.egg-info/dependency_links.txt
aegisx.ext.jose.egg-info/requires.txt
aegisx.ext.jose.egg-info/top_level.txt
aegisx/ext/jose/__init__.py
aegisx/ext/jose/_public.py
aegisx/ext/jose/cache.py
aegisx/ext/jose/const.py
aegisx/ext/jose/exc.py
aegisx/ext/jose/jwksresolver.py
aegisx/ext/jose/keyselector.py
aegisx/ext/jose/package.json
aegisx/ext/jose/tokenbuilder.py
aegisx/ext/jose/tokenkey.py
aegisx/ext/jose/tokenrecipient.py
aegisx/ext/jose/tokenvalidator.py
aegisx/ext/jose/utils.py
aegisx/ext/jose/models/__init__.py
aegisx/ext/jose/models/_asymmetrickey.py
aegisx/ext/jose/models/_fields.py
aegisx/ext/jose/models/_joseheader.py
aegisx/ext/jose/models/_jsonpublicwebkeyset.py
aegisx/ext/jose/models/_jsonwebencryption.py
aegisx/ext/jose/models/_jsonwebkeyset.py
aegisx/ext/jose/models/_jsonwebtoken.py
aegisx/ext/jose/models/_jwegeneralserialization.py
aegisx/ext/jose/models/_jweheader.py
aegisx/ext/jose/models/_jweheaderparamdict.py
aegisx/ext/jose/models/_jwscompactserialization.py
aegisx/ext/jose/models/_jwsflattenedserialization.py
aegisx/ext/jose/models/_jwsgeneralserialization.py
aegisx/ext/jose/models/_jwsheader.py
aegisx/ext/jose/models/_jwsvalidationbase.py
aegisx/ext/jose/models/_keyidentifier.py
aegisx/ext/jose/models/_recipient.py
aegisx/ext/jose/models/_signature.py
aegisx/ext/jose/models/jwk/__init__.py
aegisx/ext/jose/models/jwk/_jsonwebkey.py
aegisx/ext/jose/models/jwk/_jsonwebkeybase.py
aegisx/ext/jose/models/jwk/_jsonwebkeyedwardscurveprivate.py
aegisx/ext/jose/models/jwk/_jsonwebkeyedwardscurvepublic.py
aegisx/ext/jose/models/jwk/_jsonwebkeyellipticcurveprivate.py
aegisx/ext/jose/models/jwk/_jsonwebkeyellipticcurvepublic.py
aegisx/ext/jose/models/jwk/_jsonwebkeyinterface.py
aegisx/ext/jose/models/jwk/_jsonwebkeyrsaprivate.py
aegisx/ext/jose/models/jwk/_jsonwebkeyrsapublic.py
aegisx/ext/jose/models/jwk/_jsonwebkeysr25519private.py
aegisx/ext/jose/models/jwk/_jsonwebkeysr25519public.py
aegisx/ext/jose/models/jwk/_keyderiver.py
aegisx/ext/jose/models/jwk/_symmetricencryptionkey.py
